{
  "index": "/index.html",
  "assetGroups": [
    {
      "name": "app",
      "installMode": "prefetch",
      "resources": {
        "files": [
          "/favicon.ico",
          "/index.html",
          "/*.css",
          "/*.js"
        ]
      }
    },
    {
      "name": "assets",
      "installMode": "lazy",
      "updateMode": "prefetch",
      "resources": {
        "files": [
          "/assets/**"
        ]
      }
    }
  ],
  "dataGroups": [
    {
      "name": "api",
      "urls": [
        "https://bingebuddyapi.azurewebsites.net/api/**"
      ],
      "cacheConfig": {
        "strategy": "freshness",
        "maxSize": 100,
        "maxAge": "1d",
        "timeout": "3s"
      }
    },
    {
      "name": "userpics",
      "urls": [
        "https://platform-lookaside.fbsbx.com/**",
        "https://lh3.googleusercontent.com/**"
      ],
      "cacheConfig": {
        "strategy": "freshness",
        "maxSize": 100,
        "maxAge": "1d",
        "timeout": "5s"
      }
    }
  ]
}